erpc/__init__.py
erpc/arbitrator.py
erpc/basic_codec.py
erpc/client.py
erpc/codec.py
erpc/crc16.py
erpc/erpc_version.py
erpc/server.py
erpc/simple_server.py
erpc/transport.py
erpc-1.14.0.dist-info/METADATA
erpc-1.14.0.dist-info/WHEEL
erpc-1.14.0.dist-info/top_level.txt
erpc-1.14.0.dist-info/RECORD
