Metadata-Version: 2.1
Name: erpc
Version: 1.14.0
Summary: eRPC Python infrastructure
Home-page: https://github.com/embeddedrpc/erpc
Author: NXP
License: BSD 3-Clause
Keywords: rpc rpc-framework embedded multicore multiprocessor amp rpmsg_lite
Platform: UNKNOWN
Classifier: Development Status :: 5 - Production/Stable
Classifier: License :: OSI Approved :: BSD License
Classifier: Programming Language :: Python
Classifier: Intended Audience :: Developers
Classifier: Topic :: Software Development :: Embedded Systems
Classifier: Natural Language :: English
Classifier: Operating System :: MacOS :: MacOS X
Classifier: Operating System :: Microsoft :: Windows
Classifier: Operating System :: POSIX :: Linux
